src/__init__.py
src/__main__.py
src/course/__init__.py
src/course/db.py
src/course/main.py
src/serverPost/__init__.py
src/serverPost/main.py
src/teacherCourse/__init__.py
src/teacherCourse/db.py
src/teacherCourse/main.py
src/ulits/__init__.py
src/ulits/cookie.py
src/ulits/logo.py
coursePost-0.1.3.dist-info/LICENSE
coursePost-0.1.3.dist-info/METADATA
coursePost-0.1.3.dist-info/WHEEL
coursePost-0.1.3.dist-info/entry_points.txt
coursePost-0.1.3.dist-info/top_level.txt
coursePost-0.1.3.dist-info/RECORD
